README.rst
pytest_custom_nodeid.py
setup.py
pytest_custom_nodeid.egg-info/PKG-INFO
pytest_custom_nodeid.egg-info/SOURCES.txt
pytest_custom_nodeid.egg-info/dependency_links.txt
pytest_custom_nodeid.egg-info/entry_points.txt
pytest_custom_nodeid.egg-info/requires.txt
pytest_custom_nodeid.egg-info/top_level.txt
test/test_plugin.py