Metadata-Version: 1.1
Name: pytest-custom-nodeid
Version: 0.1
Summary: Custom grouping for pytest-xdist, rename test cases name and test cases nodeid, support allure report
Home-page: https://github.com/fungaegis/pytest-custom-nodeid
Author: fungaegis
Author-email: fungaegis@gmail.com
License: MIT License
Keywords: pytest,py.test,pytest_custom_nodeid,concurrency,xdist,pytest-xdist,allure,rename,name
Platform: UNKNOWN
Classifier: Framework :: Pytest
Classifier: Programming Language :: Python :: 3
Classifier: Topic :: Software Development :: Testing
Classifier: Programming Language :: Python :: 3.7
